aspose/__init__.py
aspose/ocr.cp310-win_amd64.pyd
aspose/ocr.cp311-win_amd64.pyd
aspose/ocr.cp312-win_amd64.pyd
aspose/ocr.cp313-win_amd64.pyd
aspose/ocr.cp35-win_amd64.pyd
aspose/ocr.cp36-win_amd64.pyd
aspose/ocr.cp37-win_amd64.pyd
aspose/ocr.cp38-win_amd64.pyd
aspose/ocr.cp39-win_amd64.pyd
aspose/pycore.cp310-win_amd64.pyd
aspose/pycore.cp311-win_amd64.pyd
aspose/pycore.cp312-win_amd64.pyd
aspose/pycore.cp313-win_amd64.pyd
aspose/pycore.cp35-win_amd64.pyd
aspose/pycore.cp36-win_amd64.pyd
aspose/pycore.cp37-win_amd64.pyd
aspose/pycore.cp38-win_amd64.pyd
aspose/pycore.cp39-win_amd64.pyd
aspose/pygc.cp310-win_amd64.pyd
aspose/pygc.cp311-win_amd64.pyd
aspose/pygc.cp312-win_amd64.pyd
aspose/pygc.cp313-win_amd64.pyd
aspose/pygc.cp35-win_amd64.pyd
aspose/pygc.cp36-win_amd64.pyd
aspose/pygc.cp37-win_amd64.pyd
aspose/pygc.cp38-win_amd64.pyd
aspose/pygc.cp39-win_amd64.pyd
aspose/pyreflection.cp310-win_amd64.pyd
aspose/pyreflection.cp311-win_amd64.pyd
aspose/pyreflection.cp312-win_amd64.pyd
aspose/pyreflection.cp313-win_amd64.pyd
aspose/pyreflection.cp35-win_amd64.pyd
aspose/pyreflection.cp36-win_amd64.pyd
aspose/pyreflection.cp37-win_amd64.pyd
aspose/pyreflection.cp38-win_amd64.pyd
aspose/pyreflection.cp39-win_amd64.pyd
aspose/__pyinstaller/__init__.pyi
aspose/__pyinstaller/hook-aspose.py
aspose/assemblies/ocr/Aspose.AI.LLM.dll
aspose/assemblies/ocr/Aspose.Drawing.Common.dll
aspose/assemblies/ocr/Aspose.OCR.dll
aspose/assemblies/ocr/Aspose.PDF.dll
aspose/assemblies/ocr/Microsoft.Bcl.AsyncInterfaces.dll
aspose/assemblies/ocr/Microsoft.ML.OnnxRuntime.dll
aspose/assemblies/ocr/Microsoft.Win32.SystemEvents.dll
aspose/assemblies/ocr/System.Drawing.Common.dll
aspose/assemblies/ocr/System.IO.Pipelines.dll
aspose/assemblies/ocr/System.Runtime.CompilerServices.Unsafe.dll
aspose/assemblies/ocr/System.Security.AccessControl.dll
aspose/assemblies/ocr/System.Security.Permissions.dll
aspose/assemblies/ocr/System.Security.Principal.Windows.dll
aspose_ocr_python_net-26.1.0.dist-info/METADATA
aspose_ocr_python_net-26.1.0.dist-info/WHEEL
aspose_ocr_python_net-26.1.0.dist-info/entry_points.txt
aspose_ocr_python_net-26.1.0.dist-info/top_level.txt
aspose_ocr_python_net-26.1.0.dist-info/RECORD
